{
  "region": "us-east-1",
  "dev": {
    "nimReasoningModel": "meta/llama-3.1-nemotron-nano-8b-v1",
    "nimGuardrailsModel": "nvidia/llama-3.1-nemoguard-8b-content-safety",
    "nimEvaluatorModel": "nvidia/nemo-evaluator",
    "instanceType": "ml.g5.2xlarge",
    "lambdaMemorySize": 2048,
    "lambdaTimeout": 300,
    "environment": "dev"
  },
  "prod": {
    "nimReasoningModel": "meta/llama-3.1-nemotron-nano-8b-v1",
    "nimGuardrailsModel": "nvidia/llama-3.1-nemoguard-8b-content-safety",
    "nimEvaluatorModel": "nvidia/nemo-evaluator",
    "instanceType": "ml.g5.2xlarge",
    "lambdaMemorySize": 2048,
    "lambdaTimeout": 300,
    "environment": "prod"
  }
}

